sposong/README.MD
sposong/__init__.py
sposong/requirements.txt
sposong/thirdparty.json
sposong-0.10.dist-info/LICENSE.rst
sposong-0.10.dist-info/METADATA
sposong-0.10.dist-info/WHEEL
sposong-0.10.dist-info/top_level.txt
sposong-0.10.dist-info/RECORD
