Metadata-Version: 2.1
Name: sposong
Version: 0.10
Summary: Finds similar songs
Home-page: https://github.com/hansalemaos/sposong
Author: Johannes Fischer
Author-email: aulasparticularesdealemaosp@gmail.com
License: MIT
Keywords: songs
Classifier: Development Status :: 4 - Beta
Classifier: Programming Language :: Python :: 3 :: Only
Classifier: Programming Language :: Python :: 3.10
Classifier: Topic :: Software Development :: Libraries :: Python Modules
Classifier: Topic :: Utilities
License-File: LICENSE.rst
Requires-Dist: PrettyColorPrinter
Requires-Dist: a-pandas-ex-plode-tool
Requires-Dist: a-selenium2df
Requires-Dist: a-selenium-add-special-keys
Requires-Dist: a-selenium-scroll-down-forever
Requires-Dist: flatten-everything
Requires-Dist: get-consecutive-filename
Requires-Dist: operagxdriver
Requires-Dist: pandas
Requires-Dist: selenium
Requires-Dist: ujson
